stringunitconverter/__init__.py
stringunitconverter/core.py
stringunitconverter/prefixes.json
stringunitconverter/units.json
stringunitconverter-0.4.dist-info/LICENSE.txt
stringunitconverter-0.4.dist-info/METADATA
stringunitconverter-0.4.dist-info/WHEEL
stringunitconverter-0.4.dist-info/top_level.txt
stringunitconverter-0.4.dist-info/RECORD
