Metadata-Version: 2.1
Name: stringunitconverter
Version: 0.4
Summary: Unit converter: Returns multiplier for unit conversion, with units defined as strings.
Home-page: https://gitlab.com/abaeyens/stringunitconverter
Author: Arne Baeyens
Author-email: mail@arnebaeyens.com
Keywords: unit conversion,conversion
Classifier: Development Status :: 5 - Production/Stable
Classifier: Intended Audience :: Science/Research
Classifier: Intended Audience :: Education
Classifier: Intended Audience :: Manufacturing
Classifier: License :: OSI Approved :: MIT License
Classifier: Programming Language :: Python :: 3
Classifier: Topic :: Scientific/Engineering
Classifier: Topic :: Scientific/Engineering :: Electronic Design Automation (EDA)
Classifier: Topic :: Utilities
Classifier: Operating System :: OS Independent
Requires-Python: >=3.6
License-File: LICENSE.txt
Requires-Dist: importlib-resources
